{
	"Description":"这个组件用于浏览大量网络或本地图片，图片路径可以http://链接或本地data://、source://目录，支持手势缩放原图，多图片支持左右滑动预览",
	"Keyword":"图片处理",
	"Html":{
		"MinVersion":"5.0",
		"Support":1
	},
	"Windows":{
		"MinVersion":"10",
		"Support":1
	},
	"asyncMethodes":[],
	"IOS":{
		"MinVersion":"7.0",
		"Support":1
	},
	"Properties":[
		{
			"Design":{
				"Type":"UInteger",
				"Data":[]
			},
			"DefaultValue":"0",
			"Group":"",
			"Type":"Number",
			"EditType":"1",
			"Description":"设置当前视图索引值，默认为0",
			"Type_JavaScript":"Number",
			"ID":"index",
			"Name":"索引"
		}
	],
	"Name":"图片预览",
	"Android":{
		"MinVersion":"4.0",
		"Support":1
	},
	"syncMethodes":[
		{
			"ReturnType_JavaScript":"",
			"Description":"给视图绑定显示的图片",
			"Paras":[
				{
					"DefaultValue":"",
					"Type":"Node",
					"Description":"数据结构[{ source : '', init : ''},{source :'' , init : ''}, ..... ]其中source 为原图，init为缩略图",
					"Required":1,
					"Type_JavaScript":"Node",
					"ID":"data",
					"Name":""
				}
			],
			"ID":"bindItems",
			"ReturnType":"",
			"Name":"绑定数据",
			"ReturnDesc":""
		}
	],
	"Type":"UI",
	"BBS":"",
	"Version":"Internal",
	"Events":[
		{
			"ReturnType_JavaScript":"String",
			"Description":"切换图片后触发该事件",
			"ID":"indexChanged",
			"ReturnType":"String",
			"ReturnDesc":"返回当前index值"
		},
		{
			"ReturnType_JavaScript":"Node",
			"Description":"长按图片触发",
			"ID":"longTouch",
			"ReturnType":"Node",
			"ReturnDesc":"返回当前index值，如:{'index':1}"
		},
		{
			"ReturnType_JavaScript":"Node",
			"Description":"点击图片触发",
			"ID":"touch",
			"ReturnType":"Node",
			"ReturnDesc":"返回当前index值,如：{'index':1}"
		}
	],
	"UIType":"View",
	"ID":"do_ImageBrowserView",
	"Icon":"",
	"IsContainer":"0",
	"WindowsPhone":{
		"MinVersion":"10",
		"Support":1
	}
}